migrateit/__init__.py
migrateit/__main__.py
migrateit/cli.py
migrateit/constants.py
migrateit/main.py
migrateit/tree.py
migrateit/clients/__init__.py
migrateit/clients/_client.py
migrateit/clients/_protocol.py
migrateit/clients/psql.py
migrateit/models/__init__.py
migrateit/models/changelog.py
migrateit/models/config.py
migrateit/models/migration.py
migrateit/reporters/__init__.py
migrateit/reporters/_utils.py
migrateit/reporters/errors.py
migrateit/reporters/logs.py
migrateit/reporters/output.py
migrateit-0.6.0.dist-info/licenses/LICENSE.md
tests/__init__.py
tests/plan_builder_test.py
tests/tree_utils_test.py
tests/clients/__init__.py
tests/clients/psql/__init__.py
tests/clients/psql/_base_test.py
tests/clients/psql/apply_test.py
tests/clients/psql/show_test.py
tests/clients/psql/squash_test.py
tests/clients/psql/validate_test.py
tests/cmd/__init__.py
tests/cmd/_base_test.py
tests/cmd/init_test.py
tests/cmd/new_test.py
tests/cmd/run_test.py
tests/cmd/show_test.py
tests/cmd/squash_test.py
migrateit-0.6.0.dist-info/METADATA
migrateit-0.6.0.dist-info/WHEEL
migrateit-0.6.0.dist-info/entry_points.txt
migrateit-0.6.0.dist-info/top_level.txt
migrateit-0.6.0.dist-info/RECORD
