Metadata-Version: 2.4
Name: migrateit
Version: 0.6.0
Author: Iago Santos
License: MIT
Classifier: Programming Language :: Python :: 3
Classifier: Programming Language :: Python :: 3 :: Only
Requires-Python: >=3.12
License-File: LICENSE.md
Requires-Dist: psycopg2-binary
Dynamic: license-file
